.travis.yml
AUTHORS
ChangeLog
LICENSE.txt
README.md
requirements.txt
setup.cfg
setup.py
test-requirements.txt
tox.ini
config_probe/__init__.py
config_probe/exceptions.py
config_probe.egg-info/PKG-INFO
config_probe.egg-info/SOURCES.txt
config_probe.egg-info/dependency_links.txt
config_probe.egg-info/not-zip-safe
config_probe.egg-info/pbr.json
config_probe.egg-info/requires.txt
config_probe.egg-info/top_level.txt
tests/__init__.py
tests/test_config_probe.py
tests/dict-merge/file1.yaml
tests/dict-merge/file2.yaml
tests/empty-files/json_file.json
tests/empty-files/yaml_file.yaml
tests/key-override/file1.yaml
tests/key-override/file2.yaml
tests/multi-level-files/ns1/stuff.yaml
tests/multi-level-files/ns1/subdir/stuff.yaml
tests/single-file/stuff.yaml
tests/single-file-with-namespace/stuff.json
tests/two-files-with-subdir-namespace/ns1/stuff.yaml
tests/two-files-with-subdir-namespace/ns2/stuff.yaml